balecore/Database.py
balecore/InlineKeyboard.py
balecore/Keyboard.py
balecore/ReplyKeyboard.py
balecore/__init__.py
balecore/bot.py
balecore/filter.py
balecore/funloader.py
balecore/states.py
balecore/update_wrapper.py
balecore/fun/__init__.py
balecore-1.0.3.dist-info/METADATA
balecore-1.0.3.dist-info/WHEEL
balecore-1.0.3.dist-info/top_level.txt
balecore-1.0.3.dist-info/RECORD
