Metadata-Version: 2.4
Name: BaleCore
Version: 1.0.3
Summary: Simplify Bale messenger bot development with this comprehensive library.
Author-email: Sasaninai <mohamad.html.70@gmail.com>, Hassan Vahidi <mrvahidi.ir@gmail.com>
Project-URL: Homepage, https://github.com/Rahanesh/BaleCore
Project-URL: Download, https://github.com/Rahanesh/BaleCore/releases/latest
Project-URL: Documentation, https://balecore.ir
Project-URL: Tracker, https://github.com/Rahanesh/BaleCore/issues
Project-URL: Community, https://ble.ir/balecore
Keywords: bale,messenger,bot,tapi,client,ble,botfather
Classifier: License :: OSI Approved :: MIT License
Classifier: Operating System :: OS Independent
Requires-Dist: aiohttp==3.11.14
